hatch_js/__init__.py
hatch_js/hooks.py
hatch_js/plugin.py
hatch_js/structs.py
hatch_js/utils.py
hatch_js/tests/test_projects.py
hatch_js/tests/test_project_basic/pyproject.toml
hatch_js/tests/test_project_basic/js/build.mjs
hatch_js/tests/test_project_basic/js/package.json
hatch_js/tests/test_project_basic/js/pnpm-lock.yaml
hatch_js/tests/test_project_basic/js/src/html/index.html
hatch_js/tests/test_project_basic/js/src/js/index.js
hatch_js/tests/test_project_basic/js/src/less/index.less
hatch_js/tests/test_project_basic/project/__init__.py
hatch_js-0.1.0.dist-info/METADATA
hatch_js-0.1.0.dist-info/WHEEL
hatch_js-0.1.0.dist-info/entry_points.txt
hatch_js-0.1.0.dist-info/licenses/LICENSE
hatch_js-0.1.0.dist-info/RECORD
